listrak/__init__.py
listrak/email.py
listrak/listrak.py
listrak_api_wrapper-0.1.5.dist-info/LICENSE
listrak_api_wrapper-0.1.5.dist-info/METADATA
listrak_api_wrapper-0.1.5.dist-info/WHEEL
listrak_api_wrapper-0.1.5.dist-info/top_level.txt
listrak_api_wrapper-0.1.5.dist-info/RECORD
