Metadata-Version: 2.1
Name: listrak-api-wrapper
Version: 0.1.5
Summary: Python API wrapper for the Listrak API
Home-page: https://github.com/aarongzmn/listrak-api-wrapper
Author: Aaron Guzman
Author-email: aarongzmn@gmail.com
Project-URL: Bug Tracker, https://github.com/aarongzmn/listrak-api-wrapper/issues
Classifier: Programming Language :: Python :: 3
Classifier: License :: OSI Approved :: MIT License
Classifier: Operating System :: OS Independent
Requires-Python: >=3.7
License-File: LICENSE
